functions_by_echervenko/README.md
functions_by_echervenko/math_functions.py
functions_by_echervenko-0.3.0.dist-info/WHEEL
functions_by_echervenko-0.3.0.dist-info/METADATA
functions_by_echervenko-0.3.0.dist-info/RECORD
